{
  "header": {
    "generated_timestamp": "2026-07-03T04:26:11Z",
    "btc_price": 61416.0,
    "change_24h": 2.766,
    "bid": 61416.1,
    "ask": 61416.0,
    "spread": 0.01,
    "volume_24h": 1285933347.93
  },
  "critical": {
    "btc_price": 61416.0,
    "amt_adx": 22.1,
    "amt_mtf": "1D BEARISH | 4H BULLISH | 1H NEUTRAL [DIVERGES_CVD=+1,232]",
    "candle_delta": -35.25,
    "candle_deltas_6": [
      528.22,
      187.86,
      482.17,
      87.49,
      -192.03,
      -35.25
    ],
    "cvd_per_tf": {
      "1D": -106.15,
      "4H": 1296.21,
      "1H": 1232.36
    },
    "oi_per_tf": {
      "1D": 0.0456,
      "4H": -0.2258,
      "1H": 0.0352
    },
    "session_cvd": 555.8,
    "oi_absolute_usd_billions": 6.59,
    "taker_ratio_24h": 1.125,
    "vp_poc": 60060,
    "vp_vah": 60133,
    "vp_val": 60025,
    "vp_shape": "P",
    "vp_state": "ACCEPTANCE",
    "balance_state": "DEVELOPING_BALANCE",
    "balance_width_pct": 3.83,
    "adx_regime": "TRANSITIONING"
  },
  "context": {
    "fng_value": 11,
    "vix": 16.85,
    "etf_flow_daily": -301.0,
    "etf_flow_weekly": -1046.0,
    "coinbase_premium": -0.0972,
    "equities": "SPY $747 (+0.8%) | QQQ $736 (+1.7%) | GLD $368 (-0.1%)",
    "dxy": 101.348,
    "us10y": 4.461,
    "oi_change_24h": -2.95,
    "long_short_ratio": 1.8986,
    "funding_rate": 7.478e-05,
    "cvd_24h": 2735.87,
    "black_swan_score": "0/17",
    "correlation_r": -0.4814,
    "liq_clusters": "Long: $61,400, $61,250, $61,100, $60,150, $60,100 | Short: $62,200",
    "perp_basis_pct": -0.034,
    "order_book_top5": {
      "bids": [
        {
          "price": 61415.99,
          "size": 2.80733
        },
        {
          "price": 61415.98,
          "size": 0.00035
        },
        {
          "price": 61415.97,
          "size": 0.00017
        },
        {
          "price": 61415.73,
          "size": 9e-05
        },
        {
          "price": 61415.67,
          "size": 0.01005
        }
      ],
      "asks": [
        {
          "price": 61416.0,
          "size": 0.14797
        },
        {
          "price": 61416.01,
          "size": 0.00107
        },
        {
          "price": 61416.02,
          "size": 0.00034
        },
        {
          "price": 61416.55,
          "size": 9e-05
        },
        {
          "price": 61416.56,
          "size": 0.01646
        }
      ]
    },
    "realized_vol_1h_pct": 58.54,
    "realized_vol_1d_pct": 53.08
  },
  "reference": {
    "sr_1h": "S: $58,332 / $58,080 / $57,754 | R: $60,288 / $60,577 / $60,754",
    "sr_1h_inverted": "$58,500 / $58,865",
    "sr_1d": "S:  | R: $65,000",
    "cycle": {
      "mvrv_z": 0.2511,
      "sopr": 0.9794,
      "netflow_7d": 8424.0
    },
    "cycle_composite": 25.2,
    "sth_realized_price": null,
    "options_skew_25d": -9.7
  },
  "status": {
    "source_timestamps": {
      "amt": "2026-07-03T04:26:03.753247+00:00",
      "vp": "2026-07-01T16:48:27.401177+00:00",
      "pipeline": "regime=2026-07-01 16:48 UTC | macro=2026-07-01 16:48 UTC"
    },
    "staleness_warnings": [
      "STALE regime: 2138m behind AMT",
      "STALE macro: 2138m behind AMT",
      "STALE derivs: 2138m behind AMT",
      "STALE cycle: 2138m behind AMT",
      "STALE vp: 2137m behind AMT"
    ]
  }
}