{
  "header": {
    "generated_timestamp": "2026-07-01T04:40:22Z",
    "btc_price": 59259.0,
    "change_24h": -3.408,
    "bid": 59260.5,
    "ask": 59259.18,
    "spread": 0.01,
    "volume_24h": 1342600178.25
  },
  "critical": {
    "btc_price": 59259.0,
    "amt_adx": 37.8,
    "amt_mtf": "1D BEARISH [INVALIDATED_CVD=+1,851] | 4H BEARISH | 1H BEARISH",
    "candle_delta": -13.71,
    "candle_deltas_6": [
      -258.96,
      -465.65,
      -401.41,
      -151.22,
      -374.72,
      -13.71
    ],
    "cvd_per_tf": {
      "1D": 1851.2,
      "4H": -494.99,
      "1H": -78.47
    },
    "oi_per_tf": {
      "1D": 0.1123,
      "4H": 0.2572,
      "1H": 0.0676
    },
    "session_cvd": -2065.0,
    "oi_absolute_usd_billions": 6.42,
    "taker_ratio_24h": 0.846,
    "vp_poc": 58418,
    "vp_vah": 58440,
    "vp_val": 58304,
    "vp_shape": "b",
    "vp_state": "ACCEPTANCE",
    "balance_state": "DEVELOPING_BALANCE",
    "balance_width_pct": 4.02,
    "adx_regime": "TRENDING"
  },
  "context": {
    "fng_value": 15,
    "vix": 17.57,
    "etf_flow_daily": -231.0,
    "etf_flow_weekly": -1950.0,
    "coinbase_premium": -0.1675,
    "equities": "SPY $741 (+1.0%) | QQQ $724 (+1.2%) | GLD $369 (-2.4%)",
    "dxy": 101.37,
    "us10y": 4.37,
    "oi_change_24h": 5.77,
    "long_short_ratio": 2.885,
    "funding_rate": 6.247e-05,
    "cvd_24h": -9667.15,
    "black_swan_score": "0/17",
    "correlation_r": -0.7828,
    "liq_clusters": "Long: $59,250, $59,000, $58,450, $58,400, $58,300 | Short: $60,700, $60,800",
    "perp_basis_pct": -0.0445,
    "order_book_top5": {
      "bids": [
        {
          "price": 59263.99,
          "size": 6.43509
        },
        {
          "price": 59263.98,
          "size": 0.00035
        },
        {
          "price": 59263.97,
          "size": 0.00017
        },
        {
          "price": 59263.88,
          "size": 0.16871
        },
        {
          "price": 59263.87,
          "size": 0.11643
        }
      ],
      "asks": [
        {
          "price": 59264.0,
          "size": 0.65291
        },
        {
          "price": 59264.01,
          "size": 0.00063
        },
        {
          "price": 59265.1,
          "size": 0.00018
        },
        {
          "price": 59265.11,
          "size": 9e-05
        },
        {
          "price": 59265.5,
          "size": 9e-05
        }
      ]
    },
    "realized_vol_1h_pct": 58.54,
    "realized_vol_1d_pct": 53.08
  },
  "reference": {
    "sr_1h": "S: $58,250 | R: $59,500 / $59,792 / $60,000",
    "sr_1h_inverted": "$58,500 / $58,829",
    "sr_1d": "S:  | R: ",
    "cycle": {
      "mvrv_z": null,
      "sopr": null,
      "netflow_7d": 11878.01
    },
    "cycle_composite": 26.8,
    "sth_realized_price": null,
    "options_skew_25d": -10.9
  },
  "status": {
    "source_timestamps": {
      "amt": "2026-07-01T04:40:15.753137+00:00",
      "vp": "2026-06-30T16:47:44.222739+00:00",
      "pipeline": "regime=2026-06-30 17:40 UTC | macro=2026-06-30 17:40 UTC"
    },
    "staleness_warnings": [
      "STALE regime: 660m behind AMT",
      "STALE macro: 660m behind AMT",
      "STALE derivs: 660m behind AMT",
      "STALE cycle: 660m behind AMT",
      "STALE vp: 712m behind AMT"
    ]
  }
}