{
  "mvrv_z": 0.35,
  "sopr": 1.0008,
  "puell_multiple": 0.6171,
  "netflow_7d": 2491.85,
  "sth_realized_price": null,
  "sth_net_position_change": null,
  "regime": "neutral",
  "composite_score": 30.3,
  "cycle_phase": "medium",
  "distribution": {
    "timestamp": "2026-07-06 08:46 UTC",
    "source": "blockchair.com",
    "total_addresses": 59426137,
    "total_btc": 20052777.29497096,
    "tiers": [
      {
        "range": "100+ BTC",
        "addresses": "2,079,914",
        "btc": "12,332,458",
        "pct": "61.50%",
        "pctNum": 61.5,
        "color": "#f59e0b"
      },
      {
        "range": "1 \u2013 100 BTC",
        "addresses": "950,818",
        "btc": "6,316,624",
        "pct": "31.50%",
        "pctNum": 31.5,
        "color": "#3b82f6"
      },
      {
        "range": "0.001 \u2013 1 BTC",
        "addresses": "24,364,716",
        "btc": "1,403,694",
        "pct": "7.00%",
        "pctNum": 7.0,
        "color": "#6366f1"
      },
      {
        "range": "<0.001 BTC",
        "addresses": "32,030,687",
        "btc": "6,015",
        "pct": "0.03%",
        "pctNum": 0.03,
        "color": "#64748b"
      }
    ]
  },
  "options_skew": {
    "timestamp": "2026-07-06 08:46 UTC",
    "spot": 62857.84,
    "skew_25d": -9.5,
    "put_25d_iv": 43.8,
    "call_25d_iv": 34.2,
    "put_name": "BTC-10JUL26-61000-P",
    "call_name": "BTC-10JUL26-64500-C",
    "label": "Elevated hedging \u2014 institutions buying downside protection",
    "emoji": "\ud83d\udfe1",
    "display": "\ud83d\udfe1 Options skew (25\u0394): -9.5% \u2014 elevated hedging \u2014 institutions buying downside protection"
  },
  "nupl": 0.15729999542236328,
  "rhodl_ratio": 0.11919999867677689,
  "lth_sopr_24h": 1.0637717970226381,
  "sth_sopr_24h": 1.0019715849489825,
  "supply_in_profit_share": 52.15999984741211,
  "mvrv": 1.1866999864578247,
  "realized_price": 53061.58,
  "lth_net_realized_pnl": 43646.51,
  "sth_net_realized_pnl": 132970.97,
  "utxos_1y_sopr": 1.3567224943553517,
  "hash_rate_ehs": 8.784212599493245e+20,
  "hash_rate_drawdown_pct": -35.68000030517578,
  "fee_rate_sat_vb": 0.722,
  "difficulty": 133869853540305.39,
  "_brk_fetched_at": "2026-07-06T07:21:22.231650+00:00",
  "_collected": "2026-07-06 08:47 UTC"
}
