{
  "funding_rate": 9.97e-06,
  "next_funding_time": 1782633600000,
  "mark_price": 59959.94432609,
  "open_interest_btc": 102989.595,
  "open_interest_usd": 6175250382.366557,
  "oi_history": [
    {
      "btc": 104660.5,
      "usd": 6315876824,
      "ts": 1782543600000
    },
    {
      "btc": 104724.7,
      "usd": 6338125412,
      "ts": 1782547200000
    },
    {
      "btc": 104753.4,
      "usd": 6329819599,
      "ts": 1782550800000
    },
    {
      "btc": 104764.3,
      "usd": 6327877073,
      "ts": 1782554400000
    },
    {
      "btc": 104818.2,
      "usd": 6330264326,
      "ts": 1782558000000
    },
    {
      "btc": 104514.6,
      "usd": 6305573681,
      "ts": 1782561600000
    },
    {
      "btc": 104559.9,
      "usd": 6314880853,
      "ts": 1782565200000
    },
    {
      "btc": 104674.0,
      "usd": 6339264542,
      "ts": 1782568800000
    },
    {
      "btc": 104808.5,
      "usd": 6350244569,
      "ts": 1782572400000
    },
    {
      "btc": 104509.3,
      "usd": 6355965311,
      "ts": 1782576000000
    },
    {
      "btc": 104320.6,
      "usd": 6341280312,
      "ts": 1782579600000
    },
    {
      "btc": 103760.7,
      "usd": 6277067860,
      "ts": 1782583200000
    },
    {
      "btc": 103715.3,
      "usd": 6278937358,
      "ts": 1782586800000
    },
    {
      "btc": 103739.9,
      "usd": 6239985928,
      "ts": 1782590400000
    },
    {
      "btc": 103481.9,
      "usd": 6236255123,
      "ts": 1782594000000
    },
    {
      "btc": 102939.6,
      "usd": 6194363946,
      "ts": 1782597600000
    },
    {
      "btc": 102995.0,
      "usd": 6200800122,
      "ts": 1782601200000
    },
    {
      "btc": 102912.6,
      "usd": 6174784894,
      "ts": 1782604800000
    },
    {
      "btc": 102913.2,
      "usd": 6187820384,
      "ts": 1782608400000
    },
    {
      "btc": 103015.9,
      "usd": 6200846972,
      "ts": 1782612000000
    },
    {
      "btc": 103068.3,
      "usd": 6196887779,
      "ts": 1782615600000
    },
    {
      "btc": 102980.8,
      "usd": 6196364433,
      "ts": 1782619200000
    },
    {
      "btc": 103094.5,
      "usd": 6196557500,
      "ts": 1782622800000
    },
    {
      "btc": 102977.2,
      "usd": 6174364007,
      "ts": 1782626400000
    }
  ],
  "oi_change_24h": -1.61,
  "oi_trend": "stable",
  "long_short_ratio": 2.0111,
  "long_pct": 66.79,
  "short_pct": 33.21,
  "taker_buy_ratio": 0.8626,
  "cvd_24h": 1795.33,
  "cvd_trend": "weakening",
  "coinbase_premium": -0.1425,
  "cb_label": "US demand soft",
  "_collected": "2026-06-28 06:48 UTC"
}
