{
  "funding_rate": 3.354e-05,
  "next_funding_time": 1783123200000,
  "mark_price": 62024.91787681,
  "open_interest_btc": 109049.921,
  "open_interest_usd": 6763812394.497619,
  "oi_history": [
    {
      "btc": 106827.3,
      "usd": 6585922617,
      "ts": 1783011600000
    },
    {
      "btc": 107451.5,
      "usd": 6623632013,
      "ts": 1783015200000
    },
    {
      "btc": 107204.1,
      "usd": 6618270474,
      "ts": 1783018800000
    },
    {
      "btc": 107402.0,
      "usd": 6600356399,
      "ts": 1783022400000
    },
    {
      "btc": 107446.5,
      "usd": 6614614799,
      "ts": 1783026000000
    },
    {
      "btc": 107269.4,
      "usd": 6604662858,
      "ts": 1783029600000
    },
    {
      "btc": 106996.6,
      "usd": 6574397231,
      "ts": 1783033200000
    },
    {
      "btc": 106938.5,
      "usd": 6581058038,
      "ts": 1783036800000
    },
    {
      "btc": 107296.0,
      "usd": 6576270619,
      "ts": 1783040400000
    },
    {
      "btc": 107160.8,
      "usd": 6597245213,
      "ts": 1783044000000
    },
    {
      "btc": 107176.7,
      "usd": 6582169727,
      "ts": 1783047600000
    },
    {
      "btc": 107252.4,
      "usd": 6586478202,
      "ts": 1783051200000
    },
    {
      "btc": 107318.5,
      "usd": 6591557588,
      "ts": 1783054800000
    },
    {
      "btc": 107448.0,
      "usd": 6626836192,
      "ts": 1783058400000
    },
    {
      "btc": 107531.8,
      "usd": 6632824321,
      "ts": 1783062000000
    },
    {
      "btc": 107754.6,
      "usd": 6652081041,
      "ts": 1783065600000
    },
    {
      "btc": 107594.6,
      "usd": 6622834601,
      "ts": 1783069200000
    },
    {
      "btc": 107648.9,
      "usd": 6641338731,
      "ts": 1783072800000
    },
    {
      "btc": 107911.4,
      "usd": 6678269833,
      "ts": 1783076400000
    },
    {
      "btc": 108507.5,
      "usd": 6727407041,
      "ts": 1783080000000
    },
    {
      "btc": 109518.5,
      "usd": 6785199837,
      "ts": 1783083600000
    },
    {
      "btc": 109422.3,
      "usd": 6793693156,
      "ts": 1783087200000
    },
    {
      "btc": 109272.1,
      "usd": 6790551852,
      "ts": 1783090800000
    },
    {
      "btc": 109286.4,
      "usd": 6764336699,
      "ts": 1783094400000
    }
  ],
  "oi_change_24h": 2.3,
  "oi_trend": "stable",
  "long_short_ratio": 1.6745,
  "long_pct": 62.61,
  "short_pct": 37.39,
  "taker_buy_ratio": 0.9642,
  "cvd_24h": 557.04,
  "cvd_trend": "strengthening",
  "coinbase_premium": -0.0879,
  "cb_label": "US demand soft",
  "_collected": "2026-07-03 16:48 UTC"
}
