{
  "liquidity_verdict": "HEALTHY",
  "taker_buy_ratio": 0.489,
  "taker_signal": "NORMAL",
  "cvd_trend": "NEGATIVE",
  "oi_delta": "FLAT",
  "oi_change_pct": 0.0607,
  "funding_rate": 6.12e-05,
  "funding_signal": "POSITIVE",
  "etf_flow_usd": -2000000000,
  "etf_signal": "OUTFLOW",
  "coinbase_premium": -0.0783,
  "coinbase_signal": "NEUTRAL",
  "signals_dry": 1,
  "signals_total": 4,
  "tactical_note": "All liquidity signals healthy. Normal market functioning.",
  "btc_price": 62924.0,
  "coinbase_spot": 62850.775,
  "timestamp": "2026-07-06 10:47 UTC",
  "data_age_minutes": 0
}