{
  "regime": "RANGING",
  "confidence": "LOW",
  "active_strategy": "Mean Reversion + Vol Filter",
  "suppressed_strategies": [
    "Liquidation Momentum",
    "Cross-Asset Macro Signal"
  ],
  "tactical_note": "No strong directional or risk signals. ATR elevated \u2014 loose mean reversion only.",
  "regime_age_minutes": 748,
  "previous_regime": "RANGING",
  "regime_changed": false,
  "btc_price": 64060.0,
  "atr_normalized": 5.3,
  "price_vs_20h_high": -0.99,
  "price_vs_20h_low": 4.49,
  "timestamp": "2026-07-07T00:46:00.481703+00:00",
  "generated_at": "2026-07-07T00:46:00.481703+00:00",
  "data_age_minutes": 0
}