{
  "ma50": 68158.32,
  "ma60": 70233.93,
  "rsi_14": 33.3,
  "bb_upper": 67174.12,
  "bb_lower": 57892.91,
  "bb_width": 14.84,
  "bb_mid": 62533.52,
  "atr_14": 2205.62,
  "atr_pct": 3.67,
  "change_7d": -1.69,
  "change_30d": -15.91,
  "price": 60046.0,
  "options_skew": {
    "timestamp": "2026-07-01 16:47 UTC",
    "spot": 60043.16,
    "skew_25d": -9.7,
    "put_25d_iv": 46.3,
    "call_25d_iv": 36.6,
    "put_name": "BTC-10JUL26-57000-P",
    "call_name": "BTC-10JUL26-63000-C",
    "label": "Elevated hedging \u2014 institutions buying downside protection",
    "emoji": "\ud83d\udfe1",
    "display": "\ud83d\udfe1 Options skew (25\u0394): -9.7% \u2014 elevated hedging \u2014 institutions buying downside protection"
  },
  "gamma": {
    "timestamp": "2026-07-01 16:37 UTC",
    "spot": 59999.92,
    "call_wall": 65000,
    "call_wall_oi": 7336.9,
    "put_wall": 60000,
    "put_wall_oi": 16262.400000000001,
    "call_wall_pct": 8.33,
    "put_wall_pct": 0.0,
    "gamma_bias": "SHORT",
    "gamma_effect": "AMPLIFIED (breakout-prone)",
    "call_oi_total": 52223.9,
    "put_oi_total": 73132.4,
    "options_scanned": 378
  },
  "_collected": "2026-07-01 16:48 UTC"
}
